ncreplayer/__init__.py
ncreplayer/replay.py
replayer/__init__.py
replayer/replay.py
ncreplayer-1.0.2.dist-info/LICENSE.txt
ncreplayer-1.0.2.dist-info/METADATA
ncreplayer-1.0.2.dist-info/WHEEL
ncreplayer-1.0.2.dist-info/entry_points.txt
ncreplayer-1.0.2.dist-info/top_level.txt
ncreplayer-1.0.2.dist-info/RECORD
