Metadata-Version: 2.1
Name: ncreplayer
Version: 1.0.2
Summary: Playback netCDF CF DSG files onto a Kafka topic
Home-page: https://github.com/axiom-data-science/ncreplayer
Author: Kyle Wilcox
Author-email: kyle@axds.co
License: MIT
Platform: UNKNOWN
Classifier: Development Status :: 4 - Beta
Classifier: Intended Audience :: Developers
Classifier: Intended Audience :: Science/Research
Classifier: License :: OSI Approved :: MIT License
Classifier: Operating System :: POSIX :: Linux
Classifier: Programming Language :: Python
Classifier: Topic :: Scientific/Engineering
Requires-Dist: click
Requires-Dist: easyavro (>=2.5.0)
Requires-Dist: msgpack-python
Requires-Dist: numpy
Requires-Dist: pandas
Requires-Dist: pocean-core
